{
  "timestamp": "2025-07-10T21:12:06.268Z",
  "serverUrl": "http://localhost:8080",
  "tests": {
    "environment": {
      "score": 78,
      "required": {
        "STRIPE_SECRET_KEY": true,
        "STRIPE_PUBLISHABLE_KEY": true,
        "STRIPE_WEBHOOK_SECRET": true,
        "STRIPE_PRICE_PERSONAL_MONTHLY": true,
        "STRIPE_PRICE_PERSONAL_YEARLY": true,
        "STRIPE_PRICE_PROFESSIONAL_MONTHLY": true,
        "STRIPE_PRICE_PROFESSIONAL_YEARLY": true,
        "STRIPE_PRICE_TEAM_MONTHLY": true,
        "STRIPE_PRICE_TEAM_YEARLY": true
      },
      "optional": {
        "SMTP_HOST": false,
        "SMTP_USER": false,
        "SMTP_PASS": false,
        "SENDGRID_API_KEY": false,
        "RAILWAY_URL": false
      },
      "issues": [
        "Live Stripe keys in development environment",
        "No email delivery mechanism configured"
      ]
    },
    "stripe": {
      "success": false,
      "error": "request to http://localhost:8080/api/stripe-config failed, reason: "
    },
    "webhook": {
      "tests": [
        {
          "name": "Missing Signature Header",
          "error": "request to http://localhost:8080/webhook failed, reason: ",
          "success": false
        },
        {
          "name": "Invalid Signature",
          "error": "request to http://localhost:8080/webhook failed, reason: ",
          "success": false
        }
      ],
      "overallSuccess": false
    },
    "email": {
      "nodemailer": {
        "details": {
          "host": false,
          "user": false,
          "pass": false,
          "port": "587"
        }
      },
      "sendgrid": {
        "details": {
          "apiKey": false,
          "fromEmail": false
        }
      },
      "success": false,
      "recommendation": "Configure either SMTP or SendGrid"
    },
    "security": {
      "issues": [
        "Live Stripe keys in non-production environment"
      ],
      "recommendations": [
        "Use test keys for development/staging"
      ],
      "securityScore": 80
    }
  }
}