{"httpProtocol":"HTTP/1.1","clientAcceptEncoding":"gzip, deflate, br","requestPriority":"","edgeRequestKeepAliveStatus":1,"requestHeaderNames":{},"clientTcpRtt":7,"colo":"SLC","asn":16591,"asOrganization":"Google Fiber Inc.","country":"US","isEUCountry":false,"city":"Salt Lake City","continent":"NA","region":"Utah","regionCode":"UT","timezone":"America/Denver","longitude":"-111.89105","latitude":"40.76078","postalCode":"84101","metroCode":"770","tlsVersion":"TLSv1.3","tlsCipher":"AEAD-AES256-GCM-SHA384","tlsClientRandom":"PuRan3Tolnzb3Z1DTMIt8mq970YpdmpR9rnJTolH1hM=","tlsClientCiphersSha1":"JZtiTn8H/ntxORk+XXvU2EvNoz8=","tlsClientExtensionsSha1":"Y7DIC8A6G0/aXviZ8ie/xDbJb7g=","tlsClientExtensionsSha1Le":"6e+q3vPm88rSgMTN/h7WTTxQ2wQ=","tlsExportedAuthenticator":{"clientHandshake":"eb21e5820be9623cf2d87a66641d816b9dbe958bf3e8438fc95549df7feeae60488db4502a1af2409a50e120e2fb43e1","serverHandshake":"95ec1518667b67ad2ab97625d84e3fffe4a4c9234565dda35f82cfbc320b9077641bde11622b88823fe269e1f95d1b23","clientFinished":"54c6d5d6da7e453c846a83d704f5c107b0b06e9c7649e11091be9ab07fd9ac0ec63f2ed0424660cb76d82247378a11b5","serverFinished":"f31123ea9e979f3bcc89814c0d5fe06d3efc4009f37ba34b3cd2107bebc1afda29f9bbe41d4cd594fbc542018b9234eb"},"tlsClientHelloLength":"386","tlsClientAuth":{"certPresented":"0","certVerified":"NONE","certRevoked":"0","certIssuerDN":"","certSubjectDN":"","certIssuerDNRFC2253":"","certSubjectDNRFC2253":"","certIssuerDNLegacy":"","certSubjectDNLegacy":"","certSerial":"","certIssuerSerial":"","certSKI":"","certIssuerSKI":"","certFingerprintSHA1":"","certFingerprintSHA256":"","certNotBefore":"","certNotAfter":""},"verifiedBotCategory":"","botManagement":{"corporateProxy":false,"verifiedBot":false,"jsDetection":{"passed":false},"staticResource":false,"detectionIds":{},"score":99}}